{
  "schema_version": "1.0",
  "run_id": "bamengine__s200__rep2",
  "framework": "bamengine",
  "framework_version": "0.9.2",
  "language": "python",
  "language_version": "3.13.12",
  "status": "ok",
  "error": null,
  "population": {
    "n_firms": 200,
    "n_households": 1000,
    "n_banks": 20,
    "n_agents_total": 1220
  },
  "n_periods": 1000,
  "warmup_periods": 100,
  "seed": 1002,
  "timing": {
    "init_seconds": 0.006256874999962747,
    "run_seconds": 0.5555952090071514,
    "steady_state_per_period_seconds": 0.0006173280100079461,
    "throughput_agent_steps_per_s": 1976258.942121056
  },
  "outputs": null,
  "process": {
    "wall_seconds": 1.017835374979768,
    "peak_rss_bytes": 136069120,
    "startup_seconds": 0.4559832909726538
  },
  "environment_id": "56abafd77150"
}
