{
  "schema_version": "1.0",
  "run_id": "bamengine__s5000__rep4",
  "framework": "bamengine",
  "framework_version": "0.9.2",
  "language": "python",
  "language_version": "3.13.12",
  "status": "ok",
  "error": null,
  "population": {
    "n_firms": 5000,
    "n_households": 25000,
    "n_banks": 500,
    "n_agents_total": 30500
  },
  "n_periods": 1000,
  "warmup_periods": 100,
  "seed": 1004,
  "timing": {
    "init_seconds": 0.006752916990080848,
    "run_seconds": 12.303543125002761,
    "steady_state_per_period_seconds": 0.01367060347222529,
    "throughput_agent_steps_per_s": 2231064.6389508094
  },
  "outputs": null,
  "process": {
    "wall_seconds": 13.7405625829997,
    "peak_rss_bytes": 66863104,
    "startup_seconds": 1.4302665410068585
  },
  "environment_id": "193e0fc5a5e8"
}
