{
  "schema_version": "1.0",
  "run_id": "mesa__s100__rep5",
  "framework": "mesa",
  "framework_version": "3.5.1",
  "language": "python",
  "language_version": "3.13.12",
  "status": "ok",
  "error": null,
  "population": {
    "n_firms": 100,
    "n_households": 500,
    "n_banks": 10,
    "n_agents_total": 610
  },
  "n_periods": 1000,
  "warmup_periods": 100,
  "seed": 1005,
  "timing": {
    "init_seconds": 0.0008710000111022964,
    "run_seconds": 1.4277349579933798,
    "steady_state_per_period_seconds": 0.0015863721755481998,
    "throughput_agent_steps_per_s": 384525.1507826046
  },
  "outputs": null,
  "process": {
    "wall_seconds": 2.0963254590024007,
    "peak_rss_bytes": 109707264,
    "startup_seconds": 0.6677195009979187
  },
  "environment_id": "5ec46f67c038"
}
